labs/lab1/logic_func.sv
module logic_func (
    input  logic x1, x2, x3, x4,
    output logic y
);
    assign y = (x2 & x4) | (~x1 & x3 & ~x4) | (x2 & x3) | (~x3 & x4);
endmodule

labs/lab1/tb_logic_func.sv
module tb_logic_func();
    logic x1,x2,x3,x4, y;
    logic [3:0] vec;
    logic expected; // ожидаемое значение из таблицы истинности
    logic error;
    
    logic_func dut (.*);
    
    initial begin
        $dumpfile("wave.vcd"); $dumpvars;
        for (int i=0; i<16; i++) begin
            {x1,x2,x3,x4} = i;
            #10;
            // здесь нужно сравнить y с expected (заранее вычисленным)
            // либо вычислить expected внутри тестбенча по формуле
        end
        $finish;
    end
endmodule

labs/lab1/run/wave.vcd
$date
	Sat May 16 08:47:43 2026
$end
$version
	ModelSim Version 6.5b
$end
$timescale
	1ps
$end
$scope module tb_logic_func $end
$var reg 1 ! x1 $end
$var reg 1 " x2 $end
$var reg 1 # x3 $end
$var reg 1 $ x4 $end
$var reg 1 % y $end
$var reg 4 & vec [3:0] $end
$var reg 1 ' expected $end
$var reg 1 ( error $end
$scope module dut $end
$var reg 1 ) x1 $end
$var reg 1 * x2 $end
$var reg 1 + x3 $end
$var reg 1 , x4 $end
$var reg 1 - y $end
$upscope $end
$upscope $end
$scope begin std $end
$upscope $end
$enddefinitions $end
#0
$dumpvars
0!
0"
0#
0$
0%
bx &
x'
x(
0)
0*
0+
0,
0-
$end
#10
1$
1,
1-
1%
#20
0$
0,
1#
1+
#30
1$
1,
0-
0%
#40
0$
0,
0#
0+
1"
1*
#50
1$
1,
1-
1%
#60
0$
0,
1#
1+
#70
1$
1,
#80
0$
0,
0#
0+
0"
0*
1!
1)
0-
0%
#90
1$
1,
1-
1%
#100
0$
0,
1#
1+
0-
0%
#110
1$
1,
#120
0$
0,
0#
0+
1"
1*
#130
1$
1,
1-
1%
#140
0$
0,
1#
1+
#150
1$
1,
